[
  {"mal_id": 5114, "title": "Fullmetal Alchemist: Brotherhood", "score": 9.09, "rank": 1, "popularity": 3, "year": 2009, "type": "TV", "episodes": 64},
  {"mal_id": 9253, "title": "Steins;Gate", "score": 9.07, "rank": 2, "popularity": 19, "year": 2011, "type": "TV", "episodes": 24},
  {"mal_id": 38524, "title": "Shingeki no Kyojin Season 3 Part 2", "score": 9.05, "rank": 3, "popularity": 50, "year": 2019, "type": "TV", "episodes": 10},
  {"mal_id": 42938, "title": "Fruits Basket: The Final", "score": 9.02, "rank": 4, "popularity": 273, "year": 2021, "type": "TV", "episodes": 13},
  {"mal_id": 11061, "title": "Hunter x Hunter (2011)", "score": 9.02, "rank": 5, "popularity": 15, "year": 2011, "type": "TV", "episodes": 148},
  {"mal_id": 40028, "title": "Shingeki no Kyojin: The Final Season", "score": 9.00, "rank": 6, "popularity": 18, "year": 2020, "type": "TV", "episodes": 16},
  {"mal_id": 42897, "title": "Gintama: The Final", "score": 8.99, "rank": 7, "popularity": 612, "year": 2021, "type": "Movie", "episodes": 1},
  {"mal_id": 9969, "title": "Gintama'", "score": 8.98, "rank": 8, "popularity": 354, "year": 2011, "type": "TV", "episodes": 51},
  {"mal_id": 820, "title": "Ginga Eiyuu Densetsu", "score": 8.97, "rank": 9, "popularity": 470, "year": 1988, "type": "OVA", "episodes": 110},
  {"mal_id": 28977, "title": "Gintama°", "score": 8.96, "rank": 10, "popularity": 330, "year": 2015, "type": "TV", "episodes": 51},
  {"mal_id": 15417, "title": "Gintama': Enchousen", "score": 8.91, "rank": 11, "popularity": 483, "year": 2012, "type": "TV", "episodes": 13},
  {"mal_id": 918, "title": "Gintama", "score": 8.90, "rank": 12, "popularity": 170, "year": 2006, "type": "TV", "episodes": 201},
  {"mal_id": 34096, "title": "Gintama.", "score": 8.89, "rank": 13, "popularity": 500, "year": 2017, "type": "TV", "episodes": 51},
  {"mal_id": 199, "title": "Sen to Chihiro no Kamikakushi", "score": 8.78, "rank": 14, "popularity": 93, "year": 2001, "type": "Movie", "episodes": 1},
  {"mal_id": 41467, "title": "Bleach: Sennen Kessen-hen", "score": 8.77, "rank": 15, "popularity": 147, "year": 2022, "type": "TV", "episodes": 13},
  {"mal_id": 35180, "title": "3-gatsu no Lion 2nd Season", "score": 8.76, "rank": 16, "popularity": 565, "year": 2017, "type": "TV", "episodes": 22},
  {"mal_id": 15335, "title": "Gintama Movie 2: Kanketsu-hen - Yorozuya yo Eien Nare", "score": 8.76, "rank": 17, "popularity": 1124, "year": 2013, "type": "Movie", "episodes": 1},
  {"mal_id": 39486, "title": "Gintama: The Semi-Final", "score": 8.74, "rank": 18, "popularity": 1522, "year": 2021, "type": "Special", "episodes": 2},
  {"mal_id": 9756, "title": "Mahou Shoujo Madoka★Magica", "score": 8.35, "rank": 19, "popularity": 104, "year": 2011, "type": "TV", "episodes": 12},
  {"mal_id": 1535, "title": "Death Note", "score": 8.62, "rank": 20, "popularity": 1, "year": 2006, "type": "TV", "episodes": 37},
  {"mal_id": 16498, "title": "Shingeki no Kyojin", "score": 8.55, "rank": 21, "popularity": 2, "year": 2013, "type": "TV", "episodes": 25},
  {"mal_id": 9253, "title": "Steins;Gate", "score": 9.07, "rank": 22, "popularity": 19, "year": 2011, "type": "TV", "episodes": 24},
  {"mal_id": 431, "title": "Howl no Ugoku Shiro", "score": 8.66, "rank": 23, "popularity": 165, "year": 2004, "type": "Movie", "episodes": 1},
  {"mal_id": 31043, "title": "Boku no Hero Academia", "score": 7.86, "rank": 24, "popularity": 8, "year": 2016, "type": "TV", "episodes": 13},
  {"mal_id": 1, "title": "Cowboy Bebop", "score": 8.75, "rank": 25, "popularity": 43, "year": 1998, "type": "TV", "episodes": 26},
  {"mal_id": 38000, "title": "Kimetsu no Yaiba", "score": 8.50, "rank": 26, "popularity": 4, "year": 2019, "type": "TV", "episodes": 26},
  {"mal_id": 40748, "title": "Jujutsu Kaisen", "score": 8.59, "rank": 27, "popularity": 7, "year": 2020, "type": "TV", "episodes": 24},
  {"mal_id": 30276, "title": "One Punch Man", "score": 8.49, "rank": 28, "popularity": 11, "year": 2015, "type": "TV", "episodes": 12},
  {"mal_id": 21, "title": "One Piece", "score": 8.71, "rank": 29, "popularity": 6, "year": 1999, "type": "TV", "episodes": 1000},
  {"mal_id": 20, "title": "Naruto", "score": 8.00, "rank": 30, "popularity": 10, "year": 2002, "type": "TV", "episodes": 220},
  {"mal_id": 19, "title": "Monster", "score": 8.87, "rank": 31, "popularity": 189, "year": 2004, "type": "TV", "episodes": 74},
  {"mal_id": 28851, "title": "Koe no Katachi", "score": 8.94, "rank": 32, "popularity": 45, "year": 2016, "type": "Movie", "episodes": 1},
  {"mal_id": 43608, "title": "Kaguya-sama wa Kokurasetai: Ultra Romantic", "score": 9.00, "rank": 33, "popularity": 259, "year": 2022, "type": "TV", "episodes": 13},
  {"mal_id": 32281, "title": "Kimi no Na wa.", "score": 8.84, "rank": 34, "popularity": 12, "year": 2016, "type": "Movie", "episodes": 1},
  {"mal_id": 37510, "title": "Mob Psycho 100 II", "score": 8.77, "rank": 35, "popularity": 164, "year": 2019, "type": "TV", "episodes": 13},
  {"mal_id": 33352, "title": "Violet Evergarden", "score": 8.65, "rank": 36, "popularity": 48, "year": 2018, "type": "TV", "episodes": 13},
  {"mal_id": 44511, "title": "Chainsaw Man", "score": 8.56, "rank": 37, "popularity": 21, "year": 2022, "type": "TV", "episodes": 12},
  {"mal_id": 41457, "title": "Kimetsu no Yaiba: Yuukaku-hen", "score": 8.76, "rank": 38, "popularity": 38, "year": 2021, "type": "TV", "episodes": 11},
  {"mal_id": 36838, "title": "Seishun Buta Yarou wa Bunny Girl Senpai no Yume wo Minai", "score": 8.22, "rank": 39, "popularity": 33, "year": 2018, "type": "TV", "episodes": 13},
  {"mal_id": 52991, "title": "Sousou no Frieren", "score": 9.30, "rank": 40, "popularity": 86, "year": 2023, "type": "TV", "episodes": 28},
  {"mal_id": 47194, "title": "Bocchi the Rock!", "score": 8.77, "rank": 41, "popularity": 154, "year": 2022, "type": "TV", "episodes": 12},
  {"mal_id": 50265, "title": "Spy x Family", "score": 8.49, "rank": 42, "popularity": 14, "year": 2022, "type": "TV", "episodes": 12},
  {"mal_id": 42963, "title": "Odd Taxi", "score": 8.70, "rank": 43, "popularity": 494, "year": 2021, "type": "TV", "episodes": 13},
  {"mal_id": 35247, "title": "Owarimonogatari 2nd Season", "score": 8.87, "rank": 44, "popularity": 728, "year": 2017, "type": "TV", "episodes": 7},
  {"mal_id": 42310, "title": "Cyberpunk: Edgerunners", "score": 8.61, "rank": 45, "popularity": 117, "year": 2022, "type": "ONA", "episodes": 10},
  {"mal_id": 39617, "title": "Vinland Saga Season 2", "score": 8.79, "rank": 46, "popularity": 297, "year": 2023, "type": "TV", "episodes": 24},
  {"mal_id": 37999, "title": "Kimetsu no Yaiba Movie: Mugen Ressha-hen", "score": 8.40, "rank": 47, "popularity": 71, "year": 2020, "type": "Movie", "episodes": 1},
  {"mal_id": 48316, "title": "Mob Psycho 100 III", "score": 8.81, "rank": 48, "popularity": 441, "year": 2022, "type": "TV", "episodes": 13},
  {"mal_id": 52034, "title": "Oshi no Ko", "score": 8.41, "rank": 49, "popularity": 28, "year": 2023, "type": "TV", "episodes": 11},
  {"mal_id": 40456, "title": "Kaguya-sama wa Kokurasetai: First Kiss wa Owaranai", "score": 8.81, "rank": 50, "popularity": 1131, "year": 2022, "type": "Movie", "episodes": 1}
]
